jira_mcp/__init__.py
jira_mcp/__main__.py
jira_mcp/jira_client.py
jira_mcp/server.py
jira_mcp/settings.py
jira_mcp_server-0.1.3.dist-info/METADATA
jira_mcp_server-0.1.3.dist-info/WHEEL
jira_mcp_server-0.1.3.dist-info/entry_points.txt
jira_mcp_server-0.1.3.dist-info/RECORD
