Metadata-Version: 2.4
Name: jira-mcp-server
Version: 0.1.3
Summary: An MCP server for interacting with Jira using username/password authentication.
Author-email: Your Name <you@example.com>
Requires-Python: >=3.10
Requires-Dist: anyio
Requires-Dist: fastmcp>=2.0.0
Requires-Dist: httpx>=0.25
Requires-Dist: jira>=3.0
Requires-Dist: pydantic-settings>=2.0
Requires-Dist: python-dotenv>=1.0
